{
    "A:SkI/1": [
        {
            "measure": "",
            "system": "",
            "position": "",
            "comment": ""
        }
    ],
    "A:SkI/2": [
        {
            "measure": "",
            "system": "",
            "position": "",
            "comment": ""
        }
    ],
    "A:SkI/3": [
        {
            "measure": "",
            "system": "",
            "position": "",
            "comment": ""
        }
    ],
    "A:SkI/4": [
        {
            "measure": "",
            "system": "",
            "position": "",
            "comment": ""
        }
    ]
}
